konfug.py
konfug-0.0.5.dist-info/LICENSE
konfug-0.0.5.dist-info/METADATA
konfug-0.0.5.dist-info/WHEEL
konfug-0.0.5.dist-info/top_level.txt
konfug-0.0.5.dist-info/RECORD
